redvox_base/__init__.py
redvox_base-2023.4.27.dist-info/METADATA
redvox_base-2023.4.27.dist-info/WHEEL
redvox_base-2023.4.27.dist-info/top_level.txt
redvox_base-2023.4.27.dist-info/RECORD
